[{"name":"color_changer","qualifiedName":"color_changer","href":"color_changer/color_changer-library.html","type":"library","overriddenDepth":0,"packageName":"flutter_custom_controller"},{"name":"ColorChanger","qualifiedName":"color_changer.ColorChanger","href":"color_changer/ColorChanger-class.html","type":"class","overriddenDepth":0,"packageName":"flutter_custom_controller","enclosedBy":{"name":"color_changer","type":"library"}},{"name":"ColorChanger","qualifiedName":"color_changer.ColorChanger.ColorChanger","href":"color_changer/ColorChanger/ColorChanger.html","type":"constructor","overriddenDepth":0,"packageName":"flutter_custom_controller","enclosedBy":{"name":"ColorChanger","type":"class"}},{"name":"controller","qualifiedName":"color_changer.ColorChanger.controller","href":"color_changer/ColorChanger/controller.html","type":"property","overriddenDepth":0,"packageName":"flutter_custom_controller","enclosedBy":{"name":"ColorChanger","type":"class"}},{"name":"createState","qualifiedName":"color_changer.ColorChanger.createState","href":"color_changer/ColorChanger/createState.html","type":"method","overriddenDepth":1,"packageName":"flutter_custom_controller","enclosedBy":{"name":"ColorChanger","type":"class"}},{"name":"color_changer_controller","qualifiedName":"color_changer_controller","href":"color_changer_controller/color_changer_controller-library.html","type":"library","overriddenDepth":0,"packageName":"flutter_custom_controller"},{"name":"ColorChangerController","qualifiedName":"color_changer_controller.ColorChangerController","href":"color_changer_controller/ColorChangerController-class.html","type":"class","overriddenDepth":0,"packageName":"flutter_custom_controller","enclosedBy":{"name":"color_changer_controller","type":"library"}},{"name":"ColorChangerController","qualifiedName":"color_changer_controller.ColorChangerController.ColorChangerController","href":"color_changer_controller/ColorChangerController/ColorChangerController.html","type":"constructor","overriddenDepth":0,"packageName":"flutter_custom_controller","enclosedBy":{"name":"ColorChangerController","type":"class"}},{"name":"changeColor","qualifiedName":"color_changer_controller.ColorChangerController.changeColor","href":"color_changer_controller/ColorChangerController/changeColor.html","type":"method","overriddenDepth":0,"packageName":"flutter_custom_controller","enclosedBy":{"name":"ColorChangerController","type":"class"}},{"name":"color","qualifiedName":"color_changer_controller.ColorChangerController.color","href":"color_changer_controller/ColorChangerController/color.html","type":"property","overriddenDepth":0,"packageName":"flutter_custom_controller","enclosedBy":{"name":"ColorChangerController","type":"class"}},{"name":"isAnimating","qualifiedName":"color_changer_controller.ColorChangerController.isAnimating","href":"color_changer_controller/ColorChangerController/isAnimating.html","type":"property","overriddenDepth":0,"packageName":"flutter_custom_controller","enclosedBy":{"name":"ColorChangerController","type":"class"}},{"name":"setValue","qualifiedName":"color_changer_controller.ColorChangerController.setValue","href":"color_changer_controller/ColorChangerController/setValue.html","type":"method","overriddenDepth":0,"packageName":"flutter_custom_controller","enclosedBy":{"name":"ColorChangerController","type":"class"}},{"name":"shouldStartAnimation","qualifiedName":"color_changer_controller.ColorChangerController.shouldStartAnimation","href":"color_changer_controller/ColorChangerController/shouldStartAnimation.html","type":"property","overriddenDepth":0,"packageName":"flutter_custom_controller","enclosedBy":{"name":"ColorChangerController","type":"class"}},{"name":"value","qualifiedName":"color_changer_controller.ColorChangerController.value","href":"color_changer_controller/ColorChangerController/value.html","type":"property","overriddenDepth":0,"packageName":"flutter_custom_controller","enclosedBy":{"name":"ColorChangerController","type":"class"}},{"name":"main","qualifiedName":"main","href":"main/main-library.html","type":"library","overriddenDepth":0,"packageName":"flutter_custom_controller"},{"name":"ColorChangerTest","qualifiedName":"main.ColorChangerTest","href":"main/ColorChangerTest-class.html","type":"class","overriddenDepth":0,"packageName":"flutter_custom_controller","enclosedBy":{"name":"main","type":"library"}},{"name":"ColorChangerTest","qualifiedName":"main.ColorChangerTest.ColorChangerTest","href":"main/ColorChangerTest/ColorChangerTest.html","type":"constructor","overriddenDepth":0,"packageName":"flutter_custom_controller","enclosedBy":{"name":"ColorChangerTest","type":"class"}},{"name":"createState","qualifiedName":"main.ColorChangerTest.createState","href":"main/ColorChangerTest/createState.html","type":"method","overriddenDepth":1,"packageName":"flutter_custom_controller","enclosedBy":{"name":"ColorChangerTest","type":"class"}},{"name":"MyApp","qualifiedName":"main.MyApp","href":"main/MyApp-class.html","type":"class","overriddenDepth":0,"packageName":"flutter_custom_controller","enclosedBy":{"name":"main","type":"library"}},{"name":"MyApp","qualifiedName":"main.MyApp.MyApp","href":"main/MyApp/MyApp.html","type":"constructor","overriddenDepth":0,"packageName":"flutter_custom_controller","enclosedBy":{"name":"MyApp","type":"class"}},{"name":"build","qualifiedName":"main.MyApp.build","href":"main/MyApp/build.html","type":"method","overriddenDepth":1,"packageName":"flutter_custom_controller","enclosedBy":{"name":"MyApp","type":"class"}},{"name":"main","qualifiedName":"main.main","href":"main/main.html","type":"function","overriddenDepth":0,"packageName":"flutter_custom_controller","enclosedBy":{"name":"main","type":"library"}}]
